{"spec_code":"054168","scientific_name":"Monomitopus microlepis","common_name":"細鱗單趾鼬鳚","short_description":"Rare species, known from a depth of 705 m (Ref. 34024).  Reproductive strategy possibly similar to other members of this family featuring oviparity, with oval pelagic eggs floating in a gelatinous mass (Ref. 205).","image_url":"images/hero/054168.jpg","max_length_cm":null,"max_weight_kg":null,"water_type":"salt","depth_range_m":[null,705.0],"countries_found":["Philippines"],"regions_by_country":{"Philippines":["608"]},"native_status":"native","importance":"none","iucn_status":""}