{"spec_code":"026393","scientific_name":"Xenagoniates bondi","common_name":"Long-finned glass tetra","short_description":"Reported to be aggressive fin nippers and can cut down caudal fins up to its peduncle (F.M. Greco, pers.comm. Apr/2019).","image_url":"images/hero/026393.jpg","max_length_cm":6.0,"max_weight_kg":null,"water_type":"fresh","depth_range_m":[null,null],"countries_found":["Colombia","Venezuela"],"regions_by_country":{"Colombia":["170"],"Venezuela":["862"]},"native_status":"native","importance":"commercial","iucn_status":""}