{"spec_code":"026896","scientific_name":"Schistura reidi","common_name":"Mřenka Reidova","short_description":"Most commonly found in swiftly flowing waters.  A female measuring 6.13 cm SL contained ripe ovulae 1.7 mm in diameter (Ref. 39226).","image_url":"images/hero/026896.jpg","max_length_cm":8.899999618530273,"max_weight_kg":null,"water_type":"fresh","depth_range_m":[null,null],"countries_found":["Thailand"],"regions_by_country":{"Thailand":["764"]},"native_status":"native","importance":"","iucn_status":""}