{"spec_code":"026992","scientific_name":"Yunnanilus altus","common_name":"Kõrge hiinatrull","short_description":"Inhabits small stream with moderate flowing water.  Moves slowly in shoals on the bottom.  Feeds on filamentous algae and insects.","image_url":"images/hero/026992.jpg","max_length_cm":7.079999923706055,"max_weight_kg":null,"water_type":"fresh","depth_range_m":[null,null],"countries_found":["China","Taiwan/Ch Taipei"],"regions_by_country":{"China":["156"]},"native_status":"native","importance":"","iucn_status":""}