{"spec_code":"002171","scientific_name":"Lethrinops parvidens","common_name":"Lethrinops red flush","short_description":"Appear to be common in shallow sandy areas and feeds on insect larvae and small crustaceans (Ref. 5595).","image_url":"images/hero/002171.jpg","max_length_cm":14.0,"max_weight_kg":null,"water_type":"fresh","depth_range_m":[null,null],"countries_found":["Malawi","Mozambique"],"regions_by_country":{"Malawi":["454"],"Mozambique":["508"]},"native_status":"native","importance":"commercial","iucn_status":""}