{"spec_code":"002151","scientific_name":"Lethrinops lethrinus","common_name":"Chisawasawa","short_description":"Inhabits shallow water near river outlets and also common a little upstream in those rivers.  Feeds on small invertebrates (Ref. 5595).","image_url":"images/hero/002151.jpg","max_length_cm":20.0,"max_weight_kg":null,"water_type":"fresh","depth_range_m":[0.0,20.0],"countries_found":["Malawi","Mozambique","Tanzania"],"regions_by_country":{"Malawi":["454"],"Mozambique":["508"],"Tanzania":["834"]},"native_status":"native","importance":"commercial","iucn_status":""}