{"spec_code":"002859","scientific_name":"Cyprinella galactura","common_name":"Whitetail shiner","short_description":"Inhabits rocky runs, less often in pools and riffles, of clear headwaters, creeks, and small rivers (Ref. 5723, 86798).  Feeds on terrestrial insects and drifting aquatic larvae (Ref. 10294).","image_url":"images/hero/002859.jpg","max_length_cm":15.0,"max_weight_kg":null,"water_type":"fresh","depth_range_m":[null,null],"countries_found":["USA","Alaska","Hawaii"],"regions_by_country":{"USA":["840"]},"native_status":"native","importance":"","iucn_status":""}