{"spec_code":"063089","scientific_name":"Muraenolepis trunovi","common_name":"Trunov parketnik","short_description":"","image_url":"images/hero/063089.jpg","max_length_cm":24.299999237060547,"max_weight_kg":null,"water_type":"salt","depth_range_m":[730.0,860.0],"countries_found":["French South Tr","Amsterdam I.","Bassas da India","Crozet Is.","Europa I.","Glorieuses Is.","Juan de Nova I.","Kerguelen Is.","St Paul I.","Tromelin I."],"regions_by_country":{"Kerguelen Is.":["250"]},"native_status":"","importance":"","iucn_status":""}