{"spec_code":"063132","scientific_name":"Muraenolepis andriashevi","common_name":"","short_description":"","image_url":"images/hero/063132.jpg","max_length_cm":44.5,"max_weight_kg":null,"water_type":"salt","depth_range_m":[null,1010.0],"countries_found":["French South Tr","Amsterdam I.","Bassas da India","Crozet Is.","Europa I.","Glorieuses Is.","Juan de Nova I.","Kerguelen Is.","St Paul I.","Tromelin I.","South Africa"],"regions_by_country":{"Kerguelen Is.":["250"],"South Africa":["710"]},"native_status":"native","importance":"","iucn_status":""}