{"spec_code":"063563","scientific_name":"Astyanax varzeae","common_name":"","short_description":"Inhabits headwater stream with clear water, light to moderate current and bottom consisting of stones, sand and moderate amount of vegetal debris (Ref. 72395).","image_url":"images/hero/063563.jpg","max_length_cm":8.3100004196167,"max_weight_kg":null,"water_type":"fresh","depth_range_m":[null,null],"countries_found":["Brazil"],"regions_by_country":{"Brazil":["076"]},"native_status":"native","importance":"","iucn_status":""}