{"spec_code":"063821","scientific_name":"Galaxias macronasus","common_name":"Bignose galaxias","short_description":"Collected mainly from small gravelly riffles in small streams. This fish appears to be cryptic (Ref. 75601).","image_url":"images/hero/063821.jpg","max_length_cm":7.0,"max_weight_kg":null,"water_type":"fresh","depth_range_m":[null,null],"countries_found":["New Zealand","Kermadec Is.","Chatham Is."],"regions_by_country":{"New Zealand":["554"]},"native_status":"native","importance":"none","iucn_status":""}