{"spec_code":"063981","scientific_name":"Cirrhilabrus brunneus","common_name":"Dusky fairy-warsse","short_description":"Sighted in a habitat characterised by a steep slope beginning in relatively deep water; about 10 individuals, including the holotype, were observed at 40 m, on a flat to gently sloping rubble bottom along the upper ed…","image_url":"images/hero/063981.jpg","max_length_cm":4.360000133514404,"max_weight_kg":null,"water_type":"salt","depth_range_m":[30.0,60.0],"countries_found":["China","Taiwan/Ch Taipei","Indonesia","Philippines"],"regions_by_country":{"China":["156"],"Indonesia":["360"],"Philippines":["608"]},"native_status":"native","importance":"","iucn_status":""}