{"spec_code":"063901","scientific_name":"Sternarchogiton preto","common_name":"","short_description":"Found only in channels and major side branches of large whitewater and blackwater rivers (Ref. 75769).","image_url":"images/hero/063901.jpg","max_length_cm":21.299999237060547,"max_weight_kg":null,"water_type":"fresh","depth_range_m":[null,null],"countries_found":["Brazil","Peru","Venezuela"],"regions_by_country":{"Brazil":["076"],"Peru":["604"],"Venezuela":["862"]},"native_status":"native","importance":"","iucn_status":""}