{"spec_code":"013576","scientific_name":"Brachynectes fasciatus","common_name":"Barred threefin","short_description":"Adults are found in rock pools and the upper subtidal zone.  Mostly associated with seagrass beds (Ref. 13227).  Eggs are hemispherical and covered with numerous sticky threads that anchor them in the algae on the nes…","image_url":"images/hero/013576.jpg","max_length_cm":4.099999904632568,"max_weight_kg":null,"water_type":"salt","depth_range_m":[0.0,13.0],"countries_found":["Australia"],"regions_by_country":{"Australia":["036"]},"native_status":"native","importance":"none","iucn_status":""}