{"spec_code":"013780","scientific_name":"Enchelycore octaviana","common_name":"Slenderjaw moray","short_description":"Lives between rocks, boulder strewn areas and walls.  Lurks in holes, crevices and dark recesses during the day; forage in the open at night.  Constantly opens and closes its mouth-an action required for respiration-n…","image_url":"images/hero/013780.jpg","max_length_cm":91.0,"max_weight_kg":null,"water_type":"salt","depth_range_m":[2.0,40.0],"countries_found":["Colombia","Costa Rica","Ecuador","Galapagos Is.","El Salvador","Guatemala","Honduras","Mexico","Nicaragua","Panama","Peru"],"regions_by_country":{"Colombia":["170"],"Costa Rica":["188"],"Ecuador":["218"],"Galapagos Is.":["218"],"El Salvador":["222"],"Guatemala":["320"],"Honduras":["340"],"Mexico":["484"],"Nicaragua":["558"],"Panama":["591"],"Peru":["604"]},"native_status":"native","importance":"","iucn_status":""}