{"spec_code":"006783","scientific_name":"Haplochromis mentatus","common_name":"Entonga","short_description":"Found in offshore areas, mostly in shallow waters (Ref. 126312). Based on its morphology, most probably a piscivorous species (Ref. 126312).","image_url":"images/hero/006783.jpg","max_length_cm":11.5,"max_weight_kg":null,"water_type":"fresh","depth_range_m":[null,null],"countries_found":["Uganda"],"regions_by_country":{"Uganda":["800"]},"native_status":"native","importance":"","iucn_status":""}