{"spec_code":"006911","scientific_name":"Tristramella simonis","common_name":"Tvarnun simon","short_description":"Feeds on phytoplankton, higher plants and, to a lesser extent, zooplankton.  Spawning season is from March to August and each specimen spawns at least 2-3 times during that period (Ref. 13609).","image_url":"images/hero/006911.jpg","max_length_cm":25.0,"max_weight_kg":null,"water_type":"fresh","depth_range_m":[null,null],"countries_found":["Israel","Jordan","Syria","Turkey"],"regions_by_country":{"Israel":["376"],"Jordan":["400"],"Syria":["760"],"Turkey":["792"]},"native_status":"native","importance":"","iucn_status":""}