{"spec_code":"048313","scientific_name":"Harttiella crassicauda","common_name":"Puroharttia","short_description":"Was discovered in a little forest creek, with some cascades and with sandy and rocky bottom.  The males have odontodes developed on their pectoral fins (Ref. 35381).","image_url":"images/hero/048313.jpg","max_length_cm":4.900000095367432,"max_weight_kg":null,"water_type":"fresh","depth_range_m":[null,null],"countries_found":["Suriname"],"regions_by_country":{"Suriname":["740"]},"native_status":"native","importance":"","iucn_status":""}