{"spec_code":"012170","scientific_name":"Puntius vittatus","common_name":"Greenstripe barb","short_description":"Occurs in ponds, streams and lakes in plains (Ref. 41236).  Often found in rice fields.  Enters brackish water.  Feeds mainly on filamentous algae and blue-green algae (Ref. 6028).","image_url":"images/hero/012170.jpg","max_length_cm":5.0,"max_weight_kg":null,"water_type":"brackish","depth_range_m":[null,null],"countries_found":["Sri Lanka","India","Maldives","Pakistan"],"regions_by_country":{"Sri Lanka":["144"],"India":["356"],"Maldives":["462"],"Pakistan":["586"]},"native_status":"native","importance":"none","iucn_status":""}