{"spec_code":"012456","scientific_name":"Microspathodon frontatus","common_name":"Guinea damselfish","short_description":"Adults inhabit rocks and rubble on inshore reefs (Ref. 7247).  Oviparous, distinct pairing during breeding (Ref. 205).  Eggs are demersal and adhere to the substrate (Ref. 205).  Males guard and aerate the eggs (Ref.…","image_url":"images/hero/012456.jpg","max_length_cm":17.0,"max_weight_kg":null,"water_type":"salt","depth_range_m":[0.0,5.0],"countries_found":["Cameroon","Benin","Eq Guinea","Ghana","Nigeria","Sao Tome Princ.","Togo"],"regions_by_country":{"Cameroon":["120"],"Benin":["204"],"Eq Guinea":["226"],"Ghana":["288"],"Nigeria":["566"],"Sao Tome Princ.":["678"],"Togo":["768"]},"native_status":"native","importance":"","iucn_status":""}