{"spec_code":"012597","scientific_name":"Aetomylaeus milvus","common_name":"Brown eagle-ray","short_description":"Found inshore (Ref. 9862).  Ovoviviparous (Ref. 50449).  Presumably utilized for human consumption in the western central Pacific (Ref. 9862).","image_url":"images/hero/012597.jpg","max_length_cm":null,"max_weight_kg":null,"water_type":"salt","depth_range_m":[null,null],"countries_found":["China","Taiwan/Ch Taipei","Hong Kong","India","Indonesia","Malaysia","Pakistan","Philippines","Viet Nam","Thailand"],"regions_by_country":{"China":["156"],"Taiwan/Ch Taipei":["156"],"Hong Kong":["156"],"India":["356"],"Indonesia":["360"],"Malaysia":["458"],"Pakistan":["586"],"Philippines":["608"],"Viet Nam":["704"],"Thailand":["764"]},"native_status":"native","importance":"","iucn_status":""}