{"spec_code":"012684","scientific_name":"Canthigaster ocellicincta","common_name":"Circle-barred puffer","short_description":"Inhabits invertebrate-rich inshore reef to outer reef walls where usually in caves in depths of about 25 meters or more.  Found singly or in pairs and on one occasion a small groups was observed among plate-corals on…","image_url":"images/hero/012684.jpg","max_length_cm":7.5,"max_weight_kg":null,"water_type":"salt","depth_range_m":[10.0,53.0],"countries_found":["Australia","Solomon Is.","Fiji","French Polynesia","Indonesia","Japan","Ryukyu Is.","Malaysia","New Caledonia","Palau","Papua New Guinea","Admiralty Is.","Philippines","Viet Nam","Tonga"],"regions_by_country":{"Australia":["036"],"Solomon Is.":["090"],"Fiji":["242"],"French Polynesia":["250"],"Indonesia":["360"],"Japan":["392"],"Ryukyu Is.":["392"],"Malaysia":["458"],"New Caledonia":["250"],"Palau":["585"],"Papua New Guinea":["598"],"Philippines":["608"],"Viet Nam":["704"],"Tonga":["776"]},"native_status":"native","importance":"","iucn_status":""}