{"spec_code":"067079","scientific_name":"Typhleotris mararybe","common_name":"","short_description":"Blind, cave-dwelling species; the known habitat, Grotte de Vitane, is a karst formation with nearly vertical walls, whose water level at the time of collection was approximately 10-15 m below the rim; the diameter of…","image_url":"images/hero/067079.jpg","max_length_cm":4.420000076293945,"max_weight_kg":null,"water_type":"fresh","depth_range_m":[null,null],"countries_found":["Madagascar"],"regions_by_country":{"Madagascar":["450"]},"native_status":"native","importance":"","iucn_status":""}