{"spec_code":"050746","scientific_name":"Plesiops polydactylus","common_name":"多指鮗","short_description":"Specimens collected at an unusually deep site for most <i>Plesiops</i> species, at 17 and 25-30 m (Ref. 27772).  Eggs are guarded by the male parent (Ref. 205).","image_url":"images/hero/050746.jpg","max_length_cm":4.579999923706055,"max_weight_kg":null,"water_type":"salt","depth_range_m":[17.0,30.0],"countries_found":["Fiji","Tonga"],"regions_by_country":{"Fiji":["242"],"Tonga":["776"]},"native_status":"native","importance":"","iucn_status":""}