{"spec_code":"010391","scientific_name":"Cheirodon galusdae","common_name":"Chilesalmler","short_description":"See Eigenmann (1928:44) for detailed description. Redescribed in Campos (1982:141).","image_url":"images/hero/010391.jpg","max_length_cm":5.940000057220459,"max_weight_kg":null,"water_type":"fresh","depth_range_m":[null,null],"countries_found":["Argentina","Chile","Easter I.","Juan Fernández","Desventuradas Is"],"regions_by_country":{"Argentina":["032"],"Chile":["152"]},"native_status":"native","importance":"none","iucn_status":""}