{"spec_code":"062374","scientific_name":"Gobio kubanicus","common_name":"Kuban gudgeon","short_description":"Found in a wide variety of habitats from montane rivers to small lowland streams with gravel or sand bottom.  Size reaches up to about 9 cm SL (Ref. 59043).","image_url":"images/hero/062374.jpg","max_length_cm":9.0,"max_weight_kg":null,"water_type":"fresh","depth_range_m":[null,null],"countries_found":["Russia"],"regions_by_country":{"Russia":["643"]},"native_status":"native","importance":"","iucn_status":""}