{"spec_code":"014147","scientific_name":"Synodus evermanni","common_name":"Inotted lizardfish","short_description":"Found on soft bottoms (Ref. 9348).","image_url":"images/hero/014147.jpg","max_length_cm":47.20000076293945,"max_weight_kg":0.539,"water_type":"salt","depth_range_m":[25.0,275.0],"countries_found":["Colombia","Costa Rica","Ecuador","Galapagos Is.","El Salvador","Guatemala","Honduras","Mexico","Nicaragua","Panama","Peru"],"regions_by_country":{"Colombia":["170"],"Costa Rica":["188"],"Ecuador":["218"],"El Salvador":["222"],"Guatemala":["320"],"Honduras":["340"],"Mexico":["484"],"Nicaragua":["558"],"Panama":["591"],"Peru":["604"]},"native_status":"native","importance":"","iucn_status":""}