{"spec_code":"061847","scientific_name":"Lophiobrycon weitzmani","common_name":"","short_description":"Most of the specimens were caught in a flooded/marshy area draining into the stream, with little current on a muddy bottom with a large amount of decomposing litter. Few specimens were caught in the stream itself, in…","image_url":"images/hero/061847.jpg","max_length_cm":2.890000104904175,"max_weight_kg":null,"water_type":"fresh","depth_range_m":[null,null],"countries_found":["Brazil"],"regions_by_country":{"Brazil":["076"]},"native_status":"native","importance":"","iucn_status":""}