{"spec_code":"061948","scientific_name":"Alburnus doriae","common_name":"Amirkabir's bleak","short_description":"Construction of the dam on the Zayandeh River (where it is known as <i>Petroleuciscus esfahani</i>) has altered the ecology of the river system.  However, its effects on the distribution and numbers of the new species…","image_url":"images/hero/061948.jpg","max_length_cm":12.199999809265137,"max_weight_kg":null,"water_type":"fresh","depth_range_m":[null,null],"countries_found":["Iran"],"regions_by_country":{"Iran":["364"]},"native_status":"native","importance":"","iucn_status":""}