{"spec_code":"049654","scientific_name":"Maratecoara lacortei","common_name":"Blauer Segelflossenkärpfling","short_description":"Inhabits seasonal swamps, lagoons and pools in typical savannah areas or transitional regions between savannah and forest (Ref. 57947).  Bottom spawner, 6 months incubation (Ref. 27139).","image_url":"images/hero/049654.jpg","max_length_cm":5.0,"max_weight_kg":null,"water_type":"fresh","depth_range_m":[null,null],"countries_found":["Brazil"],"regions_by_country":{"Brazil":["076"]},"native_status":"native","importance":"","iucn_status":""}