{"spec_code":"049788","scientific_name":"Melanorivulus punctatus","common_name":"Pilkkuriippuja","short_description":"Not a seasonal killifish.  Difficult to maintain in aquarium (Ref. 27139).","image_url":"images/hero/049788.jpg","max_length_cm":3.5,"max_weight_kg":null,"water_type":"fresh","depth_range_m":[null,null],"countries_found":["Argentina","Bolivia","Brazil","Paraguay"],"regions_by_country":{"Argentina":["032"],"Bolivia":["068"],"Brazil":["076"],"Paraguay":["600"]},"native_status":"native","importance":"","iucn_status":""}