{"spec_code":"008300","scientific_name":"Ophioblennius steindachneri","common_name":"Large-banded blenny","short_description":"Adults prefer the surge zone of unprotected rocky headlands with steep slopes.  They wedge themselves in crevices close to shore in shallow water, darting out to defend their territory.  Diurnal feeders that graze on…","image_url":"images/hero/008300.jpg","max_length_cm":18.0,"max_weight_kg":null,"water_type":"salt","depth_range_m":[0.0,18.0],"countries_found":["Colombia","Costa Rica","Ecuador","Galapagos Is.","El Salvador","Guatemala","Honduras","Mexico","Nicaragua","Panama","Peru"],"regions_by_country":{"Colombia":["170"],"Costa Rica":["188"],"Ecuador":["218"],"Galapagos Is.":["218"],"El Salvador":["222"],"Guatemala":["320"],"Honduras":["340"],"Mexico":["484"],"Nicaragua":["558"],"Panama":["591"],"Peru":["604"]},"native_status":"native","importance":"none","iucn_status":""}