{"spec_code":"008689","scientific_name":"Ventrifossa macroptera","common_name":"Palau grenadier","short_description":"Females with ripe eggs were taken in mid-December.  Captured in fair numbers during exploratory fishing on the Kyushu-Palau Ridge, but not known from any other area.","image_url":"images/hero/008689.jpg","max_length_cm":40.0,"max_weight_kg":null,"water_type":"salt","depth_range_m":[454.0,710.0],"countries_found":["China","Taiwan/Ch Taipei","Japan","Ryukyu Is.","Philippines","USA","Alaska","Hawaii"],"regions_by_country":{"Taiwan/Ch Taipei":["156"],"Japan":["392"],"Ryukyu Is.":["392"],"Philippines":["608"],"Hawaii":["840"]},"native_status":"native","importance":"","iucn_status":""}