{"spec_code":"008986","scientific_name":"Tylochromis aristoma","common_name":"美口球丽鱼","short_description":"Seems to feed primarily upon plants and insect larvae; maternal mouthbrooder that does not pair-bond (Ref. 52307).","image_url":"images/hero/008986.jpg","max_length_cm":19.299999237060547,"max_weight_kg":null,"water_type":"fresh","depth_range_m":[null,null],"countries_found":["Congo Dem Rp"],"regions_by_country":{"Congo Dem Rp":["180"]},"native_status":"native","importance":"","iucn_status":""}