{"spec_code":"004153","scientific_name":"Podothecus accipenserinus","common_name":"Sturgeon poacher","short_description":"Common on soft bottoms (Ref. 2850).  Feeds on worms, crustaceans, and small fishes (Ref. 4925).","image_url":"images/hero/004153.jpg","max_length_cm":30.5,"max_weight_kg":null,"water_type":"salt","depth_range_m":[2.0,710.0],"countries_found":["Canada","Russia","Kuril Is.","USA","Alaska","Hawaii"],"regions_by_country":{"Canada":["124"],"Russia":["643"],"Kuril Is.":["643"],"USA":["840"],"Alaska":["840"]},"native_status":"native","importance":"","iucn_status":""}