{"spec_code":"004474","scientific_name":"Gymnocephalus cernua","common_name":"Pope","short_description":"Inhabits eutrophic lakes, lowland and piedmont rivers.  Most abundant in estuaries \r\nof large rivers, brackish lakes with salinities up to 10-12 ppt and reservoirs.  In general, its abundance increases with increased…","image_url":"images/hero/004474.jpg","max_length_cm":25.0,"max_weight_kg":0.4,"water_type":"brackish","depth_range_m":[2.0,85.0],"countries_found":["Afghanistan","Austria","Belgium","Bulgaria","Canada","China","Taiwan/Ch Taipei","Croatia","Czechia","Denmark","Estonia","Finland","France","Tahiti","Tuamotu Is.","Marquesas Is.","Germany","Greece","Hungary","Iran","Italy","Latvia","Lithuania","Netherlands","Norway","Poland","Romania","Russia","Slovakia","Slovenia","Sweden","Switzerland","Turkey","Ukraine","UK","UK Engld Wal","UK Scotland","UK No Ireld","Ascension I.","Chagos Is.","Tristan da Cunha","Br Antarctic Tr","Cargados Carajos","USA","Alaska","Hawaii","Uzbekistan","Serbia"],"regions_by_country":{"Afghanistan":["004"],"Austria":["040"],"Belgium":["056"],"Bulgaria":["100"],"Canada":["124"],"China":["156"],"Croatia":["191"],"Czechia":["203"],"Denmark":["208"],"Estonia":["233"],"Finland":["246"],"France":["250"],"Germany":["276"],"Greece":["300"],"Hungary":["348"],"Iran":["364"],"Italy":["380"],"Latvia":["428"],"Lithuania":["440"],"Netherlands":["528"],"Norway":["578"],"Poland":["616"],"Romania":["642"],"Russia":["643"],"Slovakia":["703"],"Slovenia":["705"],"Sweden":["752"],"Switzerland":["756"],"Turkey":["792"],"Ukraine":["804"],"UK":["826"],"USA":["840"],"Uzbekistan":["860"],"Serbia":["891"]},"native_status":"native","importance":"commercial","iucn_status":""}