{"spec_code":"004680","scientific_name":"Poecilia sphenops","common_name":"Black mollie","short_description":"Feeds on worms, crustaceans, insects, plant  matter.  The black variety (Black molly) is a very popular aquarium fish and is marketed throughout the world (Ref. 1739).  In the aquarium it feeds on green algae and also…","image_url":"images/hero/004680.jpg","max_length_cm":7.5,"max_weight_kg":null,"water_type":"brackish","depth_range_m":[null,null],"countries_found":["Brazil","Colombia","Cook Is.","Czechia","El Salvador","French Polynesia","Honduras","Hong Kong","Hungary","Indonesia","Japan","Ryukyu Is.","Mexico","Curaçao I.","Nicaragua","Philippines","Saudi Arabia","Singapore","Slovakia","Trinidad Tobago","United Arab Em.","USA","Alaska","Hawaii","Venezuela"],"regions_by_country":{"Brazil":["076"],"Colombia":["170"],"Cook Is.":["554"],"Czechia":["203"],"El Salvador":["222"],"French Polynesia":["250"],"Honduras":["340"],"Hong Kong":["156"],"Hungary":["348"],"Indonesia":["360"],"Japan":["392"],"Mexico":["484"],"Curaçao I.":["528"],"Nicaragua":["558"],"Philippines":["608"],"Saudi Arabia":["682"],"Singapore":["702"],"Slovakia":["703"],"Trinidad Tobago":["780"],"United Arab Em.":["784"],"Hawaii":["840"],"Venezuela":["862"]},"native_status":"native","importance":"none","iucn_status":""}