{"spec_code":"005280","scientific_name":"Raiamas steindachneri","common_name":"Rajamas Steindachenrův","short_description":"Affinities:  meristic characters close to <i>R. nigeriensis</i> (with more number of branched rays; shorter head length and mouth). Maximum TL was recorded at 15.5 cm (Ref. 2801).","image_url":"images/hero/005280.jpg","max_length_cm":12.5,"max_weight_kg":null,"water_type":"fresh","depth_range_m":[null,null],"countries_found":["Guinea","Ivory coast","Liberia","Guinea-Bissau","Sierra Leone"],"regions_by_country":{"Guinea":["324"],"Ivory coast":["384"],"Liberia":["430"],"Guinea-Bissau":["624"],"Sierra Leone":["694"]},"native_status":"native","importance":"","iucn_status":""}