{"spec_code":"005508","scientific_name":"Gymnura natalensis","common_name":"Backwater butterfly ray","short_description":"Occurs off sandy beaches, muddy estuaries and offshore banks.  Found singly or in large groups (Ref. 5578).  Feeds on a variety of fishes, crabs and polychaete worms (Ref. 5578).  Ovoviviparous (Ref. 50449).  Ability…","image_url":"images/hero/005508.jpg","max_length_cm":250.0,"max_weight_kg":82.6,"water_type":"salt","depth_range_m":[20.0,100.0],"countries_found":["Mozambique","Namibia","South Africa","Yemen"],"regions_by_country":{"Mozambique":["508"],"Namibia":["516"],"South Africa":["710"],"Yemen":["887"]},"native_status":"native","importance":"","iucn_status":""}