{"spec_code":"069132","scientific_name":"Lufubuchromis relictus","common_name":"","short_description":"Found in river, about 15 m wide with an estimated depth of 50 cm, rocky with patches of sand and gravel and with few patches of submerged vegetation (Ref. 122072). It is suggested that this species feeds on insect lar…","image_url":"images/hero/069132.jpg","max_length_cm":9.319999694824219,"max_weight_kg":null,"water_type":"fresh","depth_range_m":[null,null],"countries_found":["Zambia"],"regions_by_country":{"Zambia":["894"]},"native_status":"native","importance":"","iucn_status":""}