{"spec_code":"069606","scientific_name":"Eleotris valadei","common_name":"","short_description":"The species is supposed to be amphidromous (Ref. 123271). It is found in the lower part of the river, near the estuary; it lives in muddy to clear rivers with sandy to gravel bottom between 0 to 5 meters in altitude (…","image_url":"images/hero/069606.jpg","max_length_cm":9.930000305175781,"max_weight_kg":null,"water_type":"fresh","depth_range_m":[0.0,5.0],"countries_found":["Mayotte","Madagascar","Reunion I.","Seychelles"],"regions_by_country":{"Mayotte":["250"],"Madagascar":["450"],"Reunion I.":["250"],"Seychelles":["690"]},"native_status":"native","importance":"","iucn_status":""}