{"spec_code":"069769","scientific_name":"Pseudogobius jeffi","common_name":"Jeff's snubnose goby","short_description":"Occurs in shallow-water estuarine, in mangrove creeks and muddy tide-pools, at 0-1 m; also in marginal habitats such as by boat ramps and overgrown drains. Associated with <i>P. aquilonius, P. eos</i> (minor overlap)…","image_url":"images/hero/069769.jpg","max_length_cm":3.049999952316284,"max_weight_kg":null,"water_type":"brackish","depth_range_m":[null,null],"countries_found":["Australia"],"regions_by_country":{"Australia":["036"]},"native_status":"native","importance":"","iucn_status":""}