{"spec_code":"059258","scientific_name":"Gobiodon fulvus","common_name":"棕褐叶鰕虎鱼","short_description":"A coral-commensal species (Ref. 72446).","image_url":"images/hero/059258.jpg","max_length_cm":1.2400000095367432,"max_weight_kg":null,"water_type":"salt","depth_range_m":[null,null],"countries_found":["China","Taiwan/Ch Taipei","Japan","Ryukyu Is.","Philippines","South Africa","UK","UK Engld Wal","UK Scotland","UK No Ireld","Ascension I.","Chagos Is.","Tristan da Cunha","Br Antarctic Tr","Cargados Carajos"],"regions_by_country":{"Taiwan/Ch Taipei":["156"],"Japan":["392"],"Philippines":["608"],"South Africa":["710"],"Chagos Is.":["826"]},"native_status":"native","importance":"","iucn_status":""}