{"spec_code":"068373","scientific_name":"Rasboroides pallidus","common_name":"Pallidus rasbora","short_description":"Found in shallow, slow-flowing, densely shaded lowland rain-forested streams with a sandy-silt\r\nsubstrate (Ref. 94541).","image_url":"images/hero/068373.jpg","max_length_cm":3.549999952316284,"max_weight_kg":null,"water_type":"fresh","depth_range_m":[null,null],"countries_found":["Sri Lanka"],"regions_by_country":{"Sri Lanka":["144"]},"native_status":"native","importance":"","iucn_status":""}