{"spec_code":"068556","scientific_name":"Kelloggella avaiki","common_name":"Star-spangled goby","short_description":"Specimens were collected from the lower intertidal zone on a narrow reef flat exposed to strong wave energy and were found living in small water-filled crevices in the reef pavement. Observed to be fairly abundant on…","image_url":"images/hero/068556.jpg","max_length_cm":2.0999999046325684,"max_weight_kg":null,"water_type":"salt","depth_range_m":[0.0,20.0],"countries_found":["Niue"],"regions_by_country":{"Niue":["554"]},"native_status":"native","importance":"","iucn_status":""}