{"spec_code":"068875","scientific_name":"Boehlkea weitzmani","common_name":"","short_description":"Occurs in small upland forest streams with 1.1-2.7 m width, 0.07-0.33 m depth, and 0.20-0.42 m/s) current velocity draining to both margins of the rio Japurá.  The streams are characterized by the following: clear to…","image_url":"images/hero/068875.jpg","max_length_cm":3.4800000190734863,"max_weight_kg":null,"water_type":"fresh","depth_range_m":[null,null],"countries_found":["Brazil"],"regions_by_country":{"Brazil":["076"]},"native_status":"native","importance":"","iucn_status":""}