{"spec_code":"011362","scientific_name":"Enteromius gurneyi","common_name":"Redtail barb","short_description":"Common at altitudes of 300-1000 m, especially in clear streams of the sandstone belt.  Prefers pools, where it is frequently the only fish species present apart from eels.  It thus represents an important link in the…","image_url":"images/hero/011362.jpg","max_length_cm":10.0,"max_weight_kg":null,"water_type":"fresh","depth_range_m":[null,null],"countries_found":["South Africa"],"regions_by_country":{"South Africa":["710"]},"native_status":"native","importance":"commercial","iucn_status":""}