{"spec_code":"003285","scientific_name":"Hippocampus reidi","common_name":"Longsnout seahorse","short_description":"Uncommon in most areas, but may be locally common in certain places.  Usually attached to gorgonians or seagrasses but may occur in floating <i>Sargassum</i> or swimming freely in midwater (Ref. 9710).  Ovoviviparous…","image_url":"images/hero/003285.jpg","max_length_cm":17.5,"max_weight_kg":null,"water_type":"salt","depth_range_m":[0.0,60.0],"countries_found":["Bahamas","Barbados","Bermuda","Brazil","Belize","Virgin Is. (UK)","Cayman Is.","Colombia","Cuba","French Guiana","Grenada","Haiti","Honduras","Jamaica","Mexico","Bon. Eust. Saba","Nicaragua","Panama","Puerto Rico","St Lucia","Suriname","Trinidad Tobago","Turks Caicos Is.","USA","Alaska","Hawaii","Virgin Is. (US)","Venezuela"],"regions_by_country":{"Bahamas":["044"],"Barbados":["052"],"Bermuda":["060"],"Brazil":["076"],"Belize":["084"],"Virgin Is. (UK)":["826"],"Cayman Is.":["136"],"Colombia":["170"],"Cuba":["192"],"French Guiana":["250"],"Grenada":["308"],"Haiti":["332"],"Honduras":["340"],"Jamaica":["388"],"Mexico":["484"],"Bon. Eust. Saba":["528"],"Nicaragua":["558"],"Panama":["591"],"Puerto Rico":["630"],"St Lucia":["662"],"Suriname":["740"],"Trinidad Tobago":["780"],"Turks Caicos Is.":["826"],"USA":["840"],"Virgin Is. (US)":["840"],"Venezuela":["862"]},"native_status":"native","importance":"commercial","iucn_status":""}