{"spec_code":"003623","scientific_name":"Amphistichus koelzi","common_name":"Calico surfperch","short_description":"Adults occur usually in sand beaches in surf (Ref. 2850).  Viviparous, female carries the developing young (Ref. 205).","image_url":"images/hero/003623.jpg","max_length_cm":31.0,"max_weight_kg":null,"water_type":"salt","depth_range_m":[0.0,9.0],"countries_found":["Canada","Mexico","USA","Alaska","Hawaii"],"regions_by_country":{"Canada":["124"],"Mexico":["484"],"USA":["840"]},"native_status":"native","importance":"commercial","iucn_status":""}