{"spec_code":"003899","scientific_name":"Tridentiger trigonocephalus","common_name":"Chameleon goby","short_description":"Found in oyster shells and crevices among barnacles and other fouling organisms (Ref. 2850). Oviparous (Ref. 205).  Eggs are deposited in nests which are guarded by the male (Ref. 205).","image_url":"images/hero/003899.jpg","max_length_cm":11.0,"max_weight_kg":null,"water_type":"salt","depth_range_m":[null,null],"countries_found":["Australia","China","Taiwan/Ch Taipei","Hong Kong","Israel","Japan","Ryukyu Is.","Korea (South)","Philippines","Russia","USA","Alaska","Hawaii"],"regions_by_country":{"Australia":["036"],"China":["156"],"Taiwan/Ch Taipei":["156"],"Hong Kong":["156"],"Israel":["376"],"Japan":["392"],"Korea (South)":["410"],"Philippines":["608"],"Russia":["643"],"USA":["840"]},"native_status":"native","importance":"","iucn_status":""}