{"spec_code":"000175","scientific_name":"Elops saurus","common_name":"Bonefish","short_description":"Occur in shallow neritic areas, over muddy bottoms (Ref. 5217).  Also found in brackish estuaries and juveniles are common in lagoons and hyper-saline bays (Ref. 5217).  Form large schools close to the shore (Ref. 998…","image_url":"images/hero/000175.jpg","max_length_cm":100.0,"max_weight_kg":10.06,"water_type":"salt","depth_range_m":[0.0,50.0],"countries_found":["Antigua Barbuda","Bahamas","Barbados","Bermuda","Brazil","Belize","China","Taiwan/Ch Taipei","Colombia","Costa Rica","Cuba","Dominica","Dominican Rp","Fiji","French Guiana","Guatemala","Guyana","Haiti","Honduras","Jamaica","Mexico","Mozambique","Curaçao I.","Aruba","Nicaragua","Panama","Puerto Rico","St Kitts Nevis","Anguilla","St Lucia","St Vincent Gren.","Seychelles","Viet Nam","Suriname","Trinidad Tobago","USA","Alaska","Hawaii","Virgin Is. (US)","Venezuela"],"regions_by_country":{"Antigua Barbuda":["028"],"Bahamas":["044"],"Barbados":["052"],"Bermuda":["060"],"Brazil":["076"],"Belize":["084"],"China":["156"],"Colombia":["170"],"Costa Rica":["188"],"Cuba":["192"],"Dominica":["212"],"Dominican Rp":["214"],"Fiji":["242"],"French Guiana":["250"],"Guatemala":["320"],"Guyana":["328"],"Haiti":["332"],"Honduras":["340"],"Jamaica":["388"],"Mexico":["484"],"Mozambique":["508"],"Curaçao I.":["528"],"Aruba":["528"],"Nicaragua":["558"],"Panama":["591"],"Puerto Rico":["630"],"St Kitts Nevis":["826"],"Anguilla":["826"],"St Lucia":["662"],"St Vincent Gren.":["670"],"Seychelles":["690"],"Viet Nam":["704"],"Suriname":["740"],"Trinidad Tobago":["780"],"USA":["840"],"Virgin Is. (US)":["840"],"Venezuela":["862"]},"native_status":"native","importance":"commercial","iucn_status":""}