{"spec_code":"000503","scientific_name":"Sebastes flavidus","common_name":"Greenie","short_description":"Form schools in open water along steeply sloping shores or above rocky reefs; also holes up amid cracks and crevices of the sea floor (Ref. 27436).  Juveniles found around floats and pilings (Ref. 27436).  Feed on pel…","image_url":"images/hero/000503.jpg","max_length_cm":66.0,"max_weight_kg":2.51,"water_type":"salt","depth_range_m":[0.0,549.0],"countries_found":["Canada","USA","Alaska","Hawaii"],"regions_by_country":{"Canada":["124"],"USA":["840"],"Alaska":["840"]},"native_status":"native","importance":"commercial","iucn_status":""}