{"spec_code":"000899","scientific_name":"Rhizoprionodon acutus","common_name":"Blacktip shark","short_description":"Found on continental shelves, often on sandy beaches and rarely in estuaries (Ref. 244).  Reported to enter freshwater and recorded several times from Cambodia as far upstream as the Great Lake (Ref. 12693).  Occurs n…","image_url":"images/hero/000899.jpg","max_length_cm":175.0,"max_weight_kg":5.0,"water_type":"salt","depth_range_m":[1.0,200.0],"countries_found":["Angola","Australia","Bahrain","Bangladesh","Brunei Darsm","Myanmar","Cambodia","Cameroon","Cape Verde","Sri Lanka","China","Taiwan/Ch Taipei","Congo","Congo Dem Rp","Benin","Eq Guinea","Djibouti","Gabon","Gambia","Ghana","Greece","Guinea","Hong Kong","India","Indonesia","Iran","Iraq","Israel","Italy","Ivory coast","Japan","Ryukyu Is.","Jordan","Kenya","Korea (South)","Kuwait","Liberia","Macau","Madagascar","Malaysia","Mauritania","Mauritius","Mozambique","Oman","Nigeria","Pakistan","Papua New Guinea","Admiralty Is.","Philippines","Portugal","Madeira Is.","Azores Is.","Guinea-Bissau","Qatar","Sao Tome Princ.","Saudi Arabia","Senegal","Seychelles","Sierra Leone","Singapore","Viet Nam","Somalia","South Africa","Sudan","Thailand","Togo","United Arab Em.","Egypt","Tanzania","Yemen","Eritrea","South Orkney Is.","Prince Edward Is","St Paul's Rocks","Balleny Is.","Scott I.","Macquarie Is.","South Shetland","Adelaide I.","Peter I I.","Elephant I.","Andaman Is.","Rodriguez I.","Cocos I. (C.R.)","Clipperton I.","Revillagigedo A.","Antarctica","Ogasawara Is.","Lord Howe I.","Trind. M.Vaz Is.","Socotra Arch."],"regions_by_country":{"Angola":["024"],"Australia":["036"],"Bahrain":["048"],"Bangladesh":["050"],"Brunei Darsm":["096"],"Myanmar":["104"],"Cambodia":["116"],"Cameroon":["120"],"Cape Verde":["132"],"Sri Lanka":["144"],"China":["156"],"Taiwan/Ch Taipei":["156"],"Congo":["178"],"Congo Dem Rp":["180"],"Benin":["204"],"Eq Guinea":["226"],"Djibouti":["262"],"Gabon":["266"],"Gambia":["270"],"Ghana":["288"],"Greece":["300"],"Guinea":["324"],"Hong Kong":["156"],"India":["356"],"Indonesia":["360"],"Iran":["364"],"Iraq":["368"],"Israel":["376"],"Italy":["380"],"Ivory coast":["384"],"Japan":["392"],"Jordan":["400"],"Kenya":["404"],"Korea (South)":["410"],"Kuwait":["414"],"Liberia":["430"],"Macau":["156"],"Madagascar":["450"],"Malaysia":["458"],"Mauritania":["478"],"Mauritius":["480"],"Mozambique":["508"],"Oman":["512"],"Nigeria":["566"],"Pakistan":["586"],"Papua New Guinea":["598"],"Philippines":["608"],"Madeira Is.":["620"],"Guinea-Bissau":["624"],"Qatar":["634"],"Sao Tome Princ.":["678"],"Saudi Arabia":["682"],"Senegal":["686"],"Seychelles":["690"],"Sierra Leone":["694"],"Singapore":["702"],"Viet Nam":["704"],"Somalia":["706"],"South Africa":["710"],"Sudan":["736"],"Thailand":["764"],"Togo":["768"],"United Arab Em.":["784"],"Egypt":["818"],"Tanzania":["834"],"Yemen":["887"],"Eritrea":["232"],"Andaman Is.":["356"],"Ogasawara Is.":["392"]},"native_status":"native","importance":"commercial","iucn_status":""}