{"spec_code":"000914","scientific_name":"Sphyrna mokarran","common_name":"Great hammerhead","short_description":"A coastal-pelagic, semi-oceanic shark, found close inshore and well offshore, over the continental shelves, island terraces, and in passes and lagoons (Ref. 244, 58302).  Often bottom and reef associated at 1-80 m (Re…","image_url":"images/hero/000914.jpg","max_length_cm":610.0,"max_weight_kg":449.5,"water_type":"salt","depth_range_m":[1.0,300.0],"countries_found":["Albania","Algeria","Antigua Barbuda","Australia","Bahamas","Bahrain","Bangladesh","Barbados","Bosnia Herzegov.","Brazil","Belize","Virgin Is. (UK)","Myanmar","Cambodia","Cape Verde","Cayman Is.","Sri Lanka","China","Taiwan/Ch Taipei","Colombia","Mayotte","Costa Rica","Croatia","Cuba","Cyprus","Dominica","Dominican Rp","Ecuador","Galapagos Is.","El Salvador","France","Tahiti","Tuamotu Is.","Marquesas Is.","French Guiana","French Polynesia","Djibouti","Gabon","Gambia","Ghana","Gibraltar","Greece","Grenada","Guadeloupe","Guatemala","Guinea","Guyana","Haiti","Honduras","Hong Kong","India","Indonesia","Iran","Iraq","Israel","Italy","Jamaica","Japan","Ryukyu Is.","Jordan","Kenya","Kuwait","Lebanon","Libya","Macau","Madagascar","Malaysia","Martinique","Mauritius","Mexico","Monaco","Montenegro","Montserrat","Morocco","Mozambique","Oman","Curaçao I.","Neth Antilles","Aruba","New Caledonia","Nicaragua","Micronesia","Palau","Pakistan","Panama","Papua New Guinea","Admiralty Is.","Peru","Philippines","Pitcairn","Guinea-Bissau","Puerto Rico","Qatar","Reunion I.","St Kitts Nevis","Anguilla","St Lucia","St Vincent Gren.","Saudi Arabia","Senegal","Seychelles","Viet Nam","Slovenia","Somalia","South Africa","Spain","Canary Is.","Sudan","Suriname","Syria","Thailand","Trinidad Tobago","United Arab Em.","Tunisia","Turkey","Turks Caicos Is.","Egypt","Tanzania","USA","Alaska","Hawaii","Virgin Is. (US)","Uruguay","Venezuela","Yemen","Eritrea","South Orkney Is.","Prince Edward Is","St Paul's Rocks","Balleny Is.","Scott I.","Macquarie Is.","South Shetland","Adelaide I.","Peter I I.","Elephant I.","Andaman Is.","Rodriguez I.","Cocos I. (C.R.)","Clipperton I.","Revillagigedo A.","Antarctica","Ogasawara Is.","Lord Howe I.","Trind. M.Vaz Is.","Socotra Arch."],"regions_by_country":{"Albania":["008"],"Algeria":["012"],"Antigua Barbuda":["028"],"Australia":["036"],"Bahamas":["044"],"Bahrain":["048"],"Bangladesh":["050"],"Barbados":["052"],"Bosnia Herzegov.":["070"],"Brazil":["076"],"Belize":["084"],"Virgin Is. (UK)":["826"],"Myanmar":["104"],"Cambodia":["116"],"Cape Verde":["132"],"Cayman Is.":["136"],"Sri Lanka":["144"],"China":["156"],"Taiwan/Ch Taipei":["156"],"Colombia":["170"],"Mayotte":["250"],"Costa Rica":["188"],"Croatia":["191"],"Cuba":["192"],"Cyprus":["196"],"Dominica":["212"],"Dominican Rp":["214"],"Ecuador":["218"],"Galapagos Is.":["218"],"El Salvador":["222"],"Tahiti":["250"],"Tuamotu Is.":["250"],"French Guiana":["250"],"French Polynesia":["250"],"Djibouti":["262"],"Gabon":["266"],"Gambia":["270"],"Ghana":["288"],"Gibraltar":["826"],"Greece":["300"],"Grenada":["308"],"Guadeloupe":["250"],"Guatemala":["320"],"Guinea":["324"],"Guyana":["328"],"Haiti":["332"],"Honduras":["340"],"Hong Kong":["156"],"India":["356"],"Indonesia":["360"],"Iran":["364"],"Iraq":["368"],"Israel":["376"],"Italy":["380"],"Jamaica":["388"],"Japan":["392"],"Ryukyu Is.":["392"],"Jordan":["400"],"Kenya":["404"],"Kuwait":["414"],"Lebanon":["422"],"Libya":["434"],"Macau":["156"],"Madagascar":["450"],"Malaysia":["458"],"Martinique":["250"],"Mauritius":["480"],"Mexico":["484"],"Monaco":["492"],"Montenegro":["499"],"Montserrat":["826"],"Morocco":["504"],"Mozambique":["508"],"Oman":["512"],"Curaçao I.":["528"],"Neth Antilles":["528"],"Aruba":["528"],"New Caledonia":["250"],"Nicaragua":["558"],"Micronesia":["583"],"Palau":["585"],"Pakistan":["586"],"Panama":["591"],"Papua New Guinea":["598"],"Peru":["604"],"Philippines":["608"],"Pitcairn":["826"],"Guinea-Bissau":["624"],"Puerto Rico":["630"],"Qatar":["634"],"Reunion I.":["250"],"St Kitts Nevis":["826"],"Anguilla":["826"],"St Lucia":["662"],"St Vincent Gren.":["670"],"Saudi Arabia":["682"],"Senegal":["686"],"Seychelles":["690"],"Viet Nam":["704"],"Slovenia":["705"],"Somalia":["706"],"South Africa":["710"],"Spain":["724"],"Sudan":["736"],"Suriname":["740"],"Syria":["760"],"Thailand":["764"],"Trinidad Tobago":["780"],"United Arab Em.":["784"],"Tunisia":["788"],"Turkey":["792"],"Turks Caicos Is.":["826"],"Egypt":["818"],"Tanzania":["834"],"USA":["840"],"Hawaii":["840"],"Virgin Is. (US)":["840"],"Uruguay":["858"],"Venezuela":["862"],"Yemen":["887"],"Eritrea":["232"],"Andaman Is.":["356"]},"native_status":"native","importance":"commercial","iucn_status":""}