{"spec_code":"000958","scientific_name":"Bagre bagre","common_name":"Catfish","short_description":"Chiefly marine, common around river mouths and also entering river estuaries.  Feeds on small fishes and invertebrates, such as crustaceans.  Marketed fresh.","image_url":"images/hero/000958.jpg","max_length_cm":55.0,"max_weight_kg":0.975,"water_type":"salt","depth_range_m":[null,50.0],"countries_found":["Brazil","Colombia","French Guiana","Guyana","Nicaragua","Suriname","Trinidad Tobago","Venezuela"],"regions_by_country":{"Brazil":["076"],"Colombia":["170"],"French Guiana":["250"],"Guyana":["328"],"Nicaragua":["558"],"Suriname":["740"],"Trinidad Tobago":["780"],"Venezuela":["862"]},"native_status":"native","importance":"commercial","iucn_status":""}