{"spec_code":"022757","scientific_name":"Hypseleotris galii","common_name":"Firetail gudgeon","short_description":"Occurs in streams, ponds, swamps and drains, usually among aquatic weeds.  Juveniles feed on zooplankton while adults on insects, larvae and small crustaceans.  Breeds between October and January in response to rising…","image_url":"images/hero/022757.jpg","max_length_cm":5.5,"max_weight_kg":null,"water_type":"fresh","depth_range_m":[null,null],"countries_found":["Australia"],"regions_by_country":{"Australia":["036"]},"native_status":"native","importance":"","iucn_status":""}