{"spec_code":"022805","scientific_name":"Wheelerigobius wirtzi","common_name":"Cameroon goby","short_description":"Sublittoral, collected at about 1 m on vertical rock face (Ref. 5299).","image_url":"images/hero/022805.jpg","max_length_cm":3.5299999713897705,"max_weight_kg":null,"water_type":"salt","depth_range_m":[0.0,3.0],"countries_found":["Cameroon","Sao Tome Princ."],"regions_by_country":{"Cameroon":["120"],"Sao Tome Princ.":["678"]},"native_status":"native","importance":"","iucn_status":""}