{"spec_code":"007307","scientific_name":"Chiloglanis brevibarbis","common_name":"Short barbelled suckermouth","short_description":"Oviparous (Ref. 205). Lips greatly enlarged in a big flat sucker; occurs in rapids and fast flowing waters; clings onto stones and can even climb up waterfall; feeds on algae and aquatic insects (Ref. 36900).","image_url":"images/hero/007307.jpg","max_length_cm":6.099999904632568,"max_weight_kg":null,"water_type":"fresh","depth_range_m":[null,null],"countries_found":["Kenya","Tanzania"],"regions_by_country":{"Kenya":["404"],"Tanzania":["834"]},"native_status":"native","importance":"none","iucn_status":""}