{"spec_code":"007903","scientific_name":"Pomacanthus maculosus","common_name":"Halfmoon angelfish","short_description":"More often in silty reef areas than in rich coral growth (Ref. 30573).  Minimum depth reported taken from Ref. 9710.  Maximum depth reported taken from Ref. 127989.","image_url":"images/hero/007903.jpg","max_length_cm":50.0,"max_weight_kg":null,"water_type":"salt","depth_range_m":[4.0,60.0],"countries_found":["Bahrain","Djibouti","Iran","Iraq","Israel","Japan","Ryukyu Is.","Jordan","Kenya","Kuwait","Madagascar","Mexico","Mozambique","Oman","Qatar","Saudi Arabia","Seychelles","Somalia","South Africa","Sudan","Syria","United Arab Em.","Egypt","Tanzania","Yemen","Eritrea","South Orkney Is.","Prince Edward Is","St Paul's Rocks","Balleny Is.","Scott I.","Macquarie Is.","South Shetland","Adelaide I.","Peter I I.","Elephant I.","Andaman Is.","Rodriguez I.","Cocos I. (C.R.)","Clipperton I.","Revillagigedo A.","Antarctica","Ogasawara Is.","Lord Howe I.","Trind. M.Vaz Is.","Socotra Arch."],"regions_by_country":{"Bahrain":["048"],"Djibouti":["262"],"Iran":["364"],"Iraq":["368"],"Israel":["376"],"Japan":["392"],"Jordan":["400"],"Kenya":["404"],"Kuwait":["414"],"Madagascar":["450"],"Mexico":["484"],"Mozambique":["508"],"Oman":["512"],"Qatar":["634"],"Saudi Arabia":["682"],"Seychelles":["690"],"Somalia":["706"],"South Africa":["710"],"Sudan":["736"],"Syria":["760"],"United Arab Em.":["784"],"Egypt":["818"],"Tanzania":["834"],"Yemen":["887"],"Socotra Arch.":["887"]},"native_status":"native","importance":"commercial","iucn_status":""}