{"spec_code":"001442","scientific_name":"Sarotherodon lohbergeri","common_name":"Keppi","short_description":"Found throughout the lake, but seems to prefer zones with submerged wooden or stone structures (Ref. 52307). Usually forms schools at the surface; feeds mainly on epiphytic and epilithic filamentous algae, and the dia…","image_url":"images/hero/001442.jpg","max_length_cm":16.200000762939453,"max_weight_kg":null,"water_type":"fresh","depth_range_m":[null,null],"countries_found":["Cameroon"],"regions_by_country":{"Cameroon":["120"]},"native_status":"native","importance":"","iucn_status":""}