{"spec_code":"047004","scientific_name":"Limnichthys polyactis","common_name":"Tommyfish","short_description":"Buries itself in areas of broken shell and gravel with only the head exposed.  Darts away and dives into the sand when disturbed.","image_url":"images/hero/047004.jpg","max_length_cm":7.199999809265137,"max_weight_kg":null,"water_type":"salt","depth_range_m":[0.0,6.0],"countries_found":["New Zealand","Kermadec Is.","Chatham Is."],"regions_by_country":{"New Zealand":["554"]},"native_status":"native","importance":"","iucn_status":""}