{"spec_code":"047864","scientific_name":"Cobitis sinensis","common_name":"Siberian spiny loach","short_description":"Oviparous, with distinct pairing during breeding (Ref. 205).","image_url":"images/hero/047864.jpg","max_length_cm":15.300000190734863,"max_weight_kg":null,"water_type":"fresh","depth_range_m":[null,null],"countries_found":["China","Taiwan/Ch Taipei","Hong Kong","Korea (South)"],"regions_by_country":{"China":["156"],"Hong Kong":["156"],"Korea (South)":["410"]},"native_status":"native","importance":"","iucn_status":""}