{"spec_code":"047866","scientific_name":"Sabanejewia caspia","common_name":"Caspian spined loach","short_description":"Inhabits the lower reaches of rivers, the brackish parts of the sea in bays and near river mouths (Ref. 26334).","image_url":"images/hero/047866.jpg","max_length_cm":8.800000190734863,"max_weight_kg":3.200000047683716,"water_type":"brackish","depth_range_m":[null,null],"countries_found":["Georgia","Iran","Kazakhstan","Turkey"],"regions_by_country":{"Georgia":["268"],"Iran":["364"],"Kazakhstan":["398"],"Turkey":["792"]},"native_status":"native","importance":"","iucn_status":""}