{"spec_code":"009131","scientific_name":"Tylochromis microdon","common_name":"","short_description":"Restricted in its distribution to the lake proper and absent from the surrounding swamps and inundated forest (Ref. 52346). Predominantly a lacustrine form (unusual among Tylochromines)(Ref. 52346). Benthic microphage…","image_url":"images/hero/009131.jpg","max_length_cm":15.199999809265137,"max_weight_kg":null,"water_type":"fresh","depth_range_m":[null,null],"countries_found":["Congo Dem Rp"],"regions_by_country":{"Congo Dem Rp":["180"]},"native_status":"native","importance":"","iucn_status":""}