{"spec_code":"065782","scientific_name":"Eptatretus astrolabium","common_name":"Paapua imisuu","short_description":"The observation re the 'silty mud bottom’ were the specimen was taken, was inferred from sediment in traps retrieved.  The female holotype with several small, rounded eggs, ca. 2 mm diameter; all eggs in the mesentery…","image_url":"images/hero/065782.jpg","max_length_cm":null,"max_weight_kg":null,"water_type":"salt","depth_range_m":[null,500.0],"countries_found":["Papua New Guinea","Admiralty Is."],"regions_by_country":{"Papua New Guinea":["598"]},"native_status":"native","importance":"","iucn_status":""}