{"spec_code":"065743","scientific_name":"Neoanguilla nepalensis","common_name":"Nepali uusangerjas","short_description":"Adults inhabit dark subterranean system, usually adapted to life in dark cravens and fissures. Occasionally encountered in wells or pits, they sometimes burrow into soft bottom sediments (Ref. 85009).","image_url":"images/hero/065743.jpg","max_length_cm":3.299999952316284,"max_weight_kg":null,"water_type":"fresh","depth_range_m":[null,null],"countries_found":["Nepal"],"regions_by_country":{"Nepal":["524"]},"native_status":"native","importance":"","iucn_status":""}