{"spec_code":"025278","scientific_name":"Cyclothone signata","common_name":"Showy bristlemouth","short_description":"Epipelagic and mesopelagic species, usually in upper 800 m depth with abundance maximum in upper 100 and 400-500 m (Ref. 35800).  Bathypelagic (Ref. 58302).  Oviparous, with planktonic eggs and larvae (Ref. 35800).","image_url":"images/hero/025278.jpg","max_length_cm":3.0,"max_weight_kg":null,"water_type":"salt","depth_range_m":[16.0,4938.0],"countries_found":["Canada","Chile","Easter I.","Juan Fernández","Desventuradas Is","Ecuador","Galapagos Is.","India","Mexico","Peru","USA","Alaska","Hawaii"],"regions_by_country":{"Canada":["124"],"Chile":["152"],"Juan Fernández":["152"],"Galapagos Is.":["218"],"India":["356"],"Mexico":["484"],"Peru":["604"],"USA":["840"],"Alaska":["840"],"Hawaii":["840"]},"native_status":"native","importance":"","iucn_status":""}