{"spec_code":"025742","scientific_name":"Pimelodina flavipinnis","common_name":"Bagre","short_description":"In shallow lagoons.  Feeds on benthic organisms.","image_url":"images/hero/025742.jpg","max_length_cm":39.0,"max_weight_kg":null,"water_type":"fresh","depth_range_m":[null,null],"countries_found":["Bolivia","Brazil","Colombia","Ecuador","Galapagos Is.","Peru","Venezuela"],"regions_by_country":{"Bolivia":["068"],"Brazil":["076"],"Colombia":["170"],"Ecuador":["218"],"Peru":["604"],"Venezuela":["862"]},"native_status":"native","importance":"commercial","iucn_status":""}