{"spec_code":"070436","scientific_name":"Cirripectes matatakaro","common_name":"Suspiria blenny","short_description":"","image_url":"images/hero/070436.jpg","max_length_cm":5.78000020980835,"max_weight_kg":null,"water_type":"salt","depth_range_m":[10.0,32.0],"countries_found":["France","Tahiti","Tuamotu Is.","Marquesas Is.","French Polynesia","Johnston I.","Pitcairn"],"regions_by_country":{"Tuamotu Is.":["250"],"Marquesas Is.":["250"],"French Polynesia":["250"],"Johnston I.":["840"],"Pitcairn":["826"]},"native_status":"native","importance":"","iucn_status":""}